goldenapple
