Metadata-Version: 2.1
Name: goldenapple
Version: 0.7
Summary: Goldenapple pomodoro timer
Home-page: UNKNOWN
Author: Matthew Miguel
Author-email: mmiguel6288code@gmail.com
License: MIT
Platform: UNKNOWN
